{
  "lexicon": 1,
  "id": "com.etzhayyim.apps.shinka.generatePropagationChain",
  "defs": {
    "main": {
      "type": "procedure",
      "description": "Auto-generated stub lexicon (F-Plan F2 bootstrap 2026-04-13). Tighten schema when migrating the app.",
      "x-bootstrap": true,
      "input": {
        "encoding": "application/json",
        "schema": {
          "type": "object",
          "properties": {
            "title": {
              "type": "string"
            },
            "eventAt": {
              "type": "string"
            },
            "location": {
              "type": "string"
            },
            "description": {
              "type": "string"
            },
            "involvedActors": {
              "type": "array",
              "items": {
                "type": "object",
                "properties": {
                  "name": {
                    "type": "string"
                  }
                }
              }
            }
          },
          "required": []
        }
      },
      "output": {
        "encoding": "application/json",
        "schema": {
          "type": "object",
          "properties": {
            "error": {
              "type": "string"
            },
            "raw": {
              "type": "string"
            },
            "chain": {
              "type": "string"
            },
            "count": {
              "type": "integer"
            }
          },
          "required": []
        }
      }
    }
  }
}
